instantweather/__init__.py
instantweather/instantweather.py
instantweather-1.0.0.dist-info/METADATA
instantweather-1.0.0.dist-info/WHEEL
instantweather-1.0.0.dist-info/top_level.txt
instantweather-1.0.0.dist-info/RECORD
